LICENSE
MANIFEST.in
README.rst
fswrap.py
setup.py
fswrap.egg-info/PKG-INFO
fswrap.egg-info/SOURCES.txt
fswrap.egg-info/dependency_links.txt
fswrap.egg-info/top_level.txt
tests/atextfile.xml
tests/logo.png
tests/test_fswrap.py
tests/arootfolder/afolder/helpers.html
tests/arootfolder/afolder/index.html
tests/arootfolder/afolder/index_expected.html
tests/arootfolder/afolder/layout.html