Metadata-Version: 1.1
Name: fswrap
Version: 1.0.0
Summary: An opinionated wrapper on file system and path functions
Home-page: http://github.com/hyde/fswrap
Author: Lakshmi Vyas
Author-email: lakshmi.vyas@gmail.com
License: MIT
Platform: UNKNOWN
Classifier: Development Status :: 3 - Alpha
Classifier: Intended Audience :: Developers
Classifier: License :: OSI Approved :: MIT License
Classifier: Operating System :: OS Independent
Classifier: Programming Language :: Python
Classifier: Topic :: Software Development
